askfm_api/__init__.py
askfm_api/errors.py
askfm_api/requests.py
askfm_api-0.2.1.dist-info/WHEEL
askfm_api-0.2.1.dist-info/METADATA
askfm_api-0.2.1.dist-info/LICENSE
askfm_api-0.2.1.dist-info/RECORD
