Metadata-Version: 2.1
Name: askfm-api
Version: 0.2.1
Summary: Unofficial API wrapper for https://ask.fm
License: MIT
Author-email: snowwm <snowwontmelt@gmail.com>
Requires-Python: >=3.9
Classifier: Development Status :: 3 - Alpha
Classifier: Intended Audience :: Developers
Classifier: License :: OSI Approved :: MIT License
Classifier: Operating System :: OS Independent
Classifier: Programming Language :: Python :: 3
Classifier: Programming Language :: Python :: 3.9
Requires-Dist: requests~=2.25
Project-URL: homepage, https://github.com/AskfmForHumans/askfm-api
